CHANGES.rst
CONTRIBUTORS.rst
LICENSE
MANIFEST.in
README.rst
requirements.txt
setup.py
techies/__init__.py
techies/compat.py
techies/landmines.py
techies/stasistrap.py
techies.egg-info/PKG-INFO
techies.egg-info/SOURCES.txt
techies.egg-info/dependency_links.txt
techies.egg-info/not-zip-safe
techies.egg-info/requires.txt
techies.egg-info/top_level.txt