Metadata-Version: 1.1
Name: techies
Version: 0.2.0
Summary: Opinionated Python toolbox
Home-page: https://github.com/woozyking/techies
Author: Runzhou Li (Leo)
Author-email: runzhou.li@gmail.com
License: Copyright (c) 2014 Runzhou Li
